key_master_3000/__init__.py
key_master_3000/main.py
key_master_3000-0.1.0.dist-info/METADATA
key_master_3000-0.1.0.dist-info/WHEEL
key_master_3000-0.1.0.dist-info/entry_points.txt
key_master_3000-0.1.0.dist-info/RECORD
