Metadata-Version: 2.3
Name: key-master-3000
Version: 0.1.0
Summary: 
Author: Ole-Jakob Olsen
Author-email: ole.jakob.olsen@ngi.no
Requires-Python: >=3.12,<4.0
Classifier: Programming Language :: Python :: 3
Classifier: Programming Language :: Python :: 3.12
Classifier: Programming Language :: Python :: 3.13
Requires-Dist: azure-identity (>=1.25.1,<2.0.0)
Requires-Dist: azure-keyvault-secrets (>=4.10.0,<5.0.0)
Requires-Dist: azure-mgmt-keyvault (>=12.1.1,<13.0.0)
Requires-Dist: azure-mgmt-resource (>=24.0.0,<25.0.0)
Requires-Dist: httpx (>=0.28.1,<0.29.0)
Requires-Dist: inquirerpy (>=0.3.4,<0.4.0)
Requires-Dist: pyperclip (>=1.11.0,<2.0.0)
